__init__.py
gardena/__init__.py
gardena/base_gardena_class.py
gardena/location.py
gardena/smart_system.py
gardena/devices/__init__.py
gardena/devices/base_device.py
gardena/devices/device_factory.py
gardena/devices/mower.py
gardena/devices/power_socket.py
gardena/devices/sensor.py
gardena/devices/smart_irrigation_control.py
gardena/devices/water_control.py
py_smart_gardena2-0.7.4.dist-info/LICENSE
py_smart_gardena2-0.7.4.dist-info/METADATA
py_smart_gardena2-0.7.4.dist-info/WHEEL
py_smart_gardena2-0.7.4.dist-info/top_level.txt
py_smart_gardena2-0.7.4.dist-info/RECORD
