Metadata-Version: 2.1
Name: py-smart-gardena2
Version: 0.7.4
Summary: This library aims to provide python way to communicate with gardena smart gateway and all smart gardena systems.
Home-page: https://github.com/osks/py-smart-gardena2
Author: Oskar Skoog
Author-email: oskar@osd.se
License: MIT
Platform: UNKNOWN
Classifier: Programming Language :: Python :: 3
Classifier: License :: OSI Approved :: MIT License
Classifier: Operating System :: OS Independent
Requires-Dist: requests
Requires-Dist: oauthlib
Requires-Dist: requests-oauthlib
Requires-Dist: websocket-client
Provides-Extra: dev
Requires-Dist: pre-commit ; extra == 'dev'
